src/ControlUnit.sv
// ALU Ops:
/*
 ADD -> 00
 Sub -> 01
 Or -> 10
 AND -> 11
 */
module ControlUnit(clk, reset, current_opcode,current_func, branch_inst, reg_reg_inst, load_inst, reg_dest, alu_op);
   input logic clk;
   input logic reset;
   input logic [6:0] current_opcode;
   input logic [3:0] current_func;
   output logic branch_inst;
   output logic reg_reg_inst;
   output logic load_inst;
   output logic reg_dest;
   output logic [3:0] alu_op;
   logic              delayed_load_inst;
   
   /*
    Instructions
    1. NOP                 0000
    2. ADD                 0001
    3. SUB                 0010
    4. XOR                 0011
    5. OR                  0100
    6. AND                 0101
    7. LOGICAL SL          0110
    8. LOGICAL SR          0111
    9. ARITHM. SL          1000
    10. ARITHM. SR         1001
    11. SETLT              1010
    12. SETLT(zero extend) 1011
    
    Branch Checkers:
    12. EQ                 1100
    13. NE                 1101
    14. LT                 1110
    15. GE                 1111
    */

   
   
   always @(posedge clk) begin
      load_inst <= delayed_load_inst;
   end
   
   always_comb begin
//      if(current_opcode[6]) begin
//         // branch
//      end
      if ((current_opcode[0] & current_opcode[1]) == 1) begin
         case(current_opcode[5:4])
           2'b00: begin
              // reg reg load
              // reg reg loads are basically immediate ops with a constant alu_op
              branch_inst = 0; reg_reg_inst = 0; delayed_load_inst = 1; reg_dest = 0; alu_op = 4'b0001; //always an add
           end
           2'b01: begin
              // immediate
//              $display("immediate %b %b", current_opcode, current_func);
              branch_inst = 0; reg_reg_inst = 0; delayed_load_inst = 0; reg_dest = 0;
              case(current_func[2:0])
                3'b000: begin
                   // ADD
                   alu_op = 4'b0001;
                end
                3'b001: begin
                   //SLLI
                   alu_op = 4'b0110;
                   
                end
                3'b010: begin
                   // SETLT
                   alu_op = 4'b1010;
                   
                end
                3'b011: begin
                   // SETLT (U)
                   alu_op = 4'b1011;
                   
                end
                3'b100: begin
                   // XOR
                   alu_op = 4'b0011;
                end
                3'b101: begin
                   // Either logical SR or arith SR
                   if(current_func[3] == 0) alu_op = 4'b0111;
                   else alu_op = 4'b1001;
                end
                3'b110: begin
                  // OR
                   alu_op = 4'b0100;
                end
                3'b111: begin
                   // AND
                   alu_op = 4'b0101;
                end
                default: begin
                   alu_op = 4'b0000;
                end
              endcase // case (current_func)
              
           end
           2'b10: begin
              // store 
              branch_inst = 0; reg_reg_inst = 0; delayed_load_inst = 1; reg_dest = 0; alu_op = 4'b0000;
           end
           2'b11: begin
              // reg reg arith
//              $display("reg reg arith %b %b", current_opcode, current_func);
              branch_inst = 0; reg_reg_inst = 1; delayed_load_inst = 0; reg_dest = 0;
              case (current_func)
                4'b0000: alu_op = 4'b0001;
                4'b1000: alu_op = 4'b0010;
                4'b0001: alu_op = 4'b0110;
                4'b0010: alu_op = 4'b1010;
                4'b0011: alu_op = 4'b1011;
                4'b0100: alu_op = 4'b0011;
                4'b0101: alu_op = 4'b0111;
                4'b1101: alu_op = 4'b1001;
                4'b0110: alu_op = 4'b0100;
                4'b0111: alu_op = 4'b0101;
                default: alu_op = 4'b0000;
              endcase // case (current_func[2:0])
           end
         endcase // case (current_opcode[6:4])
      end // if (opcode[0] & opcode[1] == 1)
      else begin
         // illegal instruction or nop
         branch_inst = 0;reg_reg_inst = 0; delayed_load_inst = 0; reg_dest = 0; alu_op = 4'b0000;
      end // else: !if((current_opcode[0] & current_opcode[1]) == 1)
      
   end
endmodule; // ControlUnit

src/Regfile.sv
module Regfile (clk, reset, reg_a, ra_data, reg_b, rb_data, reg_wa, wa_data, reg_r_w, reg_array);
   input logic clk;
   input logic reset;

   input logic [4:0] reg_a;
   input logic [4:0] reg_b;
   output logic [31:0] ra_data;
   output logic [31:0] rb_data;
   input logic [4:0]   reg_wa;
   input logic [31:0]  wa_data;

   input logic         reg_r_w;

   output logic [31:0]        reg_array [31:0];
   // constant first register 
   assign reg_array[0] = 0;
   
   
   

   always @(posedge clk) begin
      if(reset) begin
         ra_data <= 0;
         rb_data <= 0;
      end
      else begin
         ra_data <= reg_array[reg_a];
         rb_data <= reg_array[reg_b];
         reg_array[reg_wa] <= wa_data;
      end
      
      
   end
   
   
   
endmodule; // Regfile

src/DMem.sv
module DMem(clk, address, in, out, en, r_w);
   input logic clk;
   
   input logic [31:0] in;
   
   input logic [31:0] address;
   input logic        en;
   input logic        r_w;
   output logic [31:0] out;
   
   logic [31:0]        dmem [2047:0];
   assign dmem[1] = 69;
   

   always @(posedge clk) begin
      if(en) begin
         if(!r_w) out <= dmem[address];
         else dmem[address] <= in;
      end
      else begin
         out <= 0;
      end
      
   end
endmodule // DMem

src/Stage4.sv
module Stage4(clk, reset, load_inst, ex_mem_ir, ex_mem_alu_output, ex_mem_b, mem_wb);
   input logic clk;
   input logic reset;
   input logic load_inst;
   input logic [31:0] ex_mem_ir;
   input logic [31:0] ex_mem_alu_output;
   input logic [31:0] ex_mem_b;
   output logic [31:0] mem_wb [3:0];
   logic [31:0]        mem_out;
   logic               r_w;
   
   DMem dm(clk, ex_mem_alu_output, ex_mem_b, mem_wb[2], load_inst, r_w);
   
   always @(posedge clk) begin
      mem_wb[0] <= ex_mem_ir;
      mem_wb[1] <= ex_mem_alu_output;
      mem_wb[3] <= load_inst;
   end
   
   
endmodule; // Stage4

src/ALU.sv
module ALU(alu_a, alu_b, alu_op, alu_out);
   input logic [31:0] alu_a;
   input logic [31:0] alu_b;
   input logic [3:0]  alu_op;
   output logic [31:0] alu_out;



   always_comb begin
      case (alu_op)
        4'b0001: alu_out = alu_a + alu_b;
        4'b0010: alu_out = alu_a - alu_b;
        4'b0011: alu_out = alu_a ^ alu_b;
        4'b0100: alu_out = alu_a | alu_b;
        4'b0101: alu_out = alu_a & alu_b;
        4'b0110: alu_out = alu_a << alu_b;
        4'b0111: alu_out = alu_a >> alu_b;
        4'b1000: alu_out = alu_a <<< alu_b;
        4'b1001: alu_out = alu_a >>> alu_b;
        4'b1010: alu_out = (alu_a < alu_b) ? 1 : 0;
        4'b1011: alu_out = (alu_a < alu_b) ? 1 : 0;
        
        default: begin
           alu_out = 0;
        end
        
        
      endcase // case alu_op
      
   end
   
   
endmodule; // ALU

src/Stage3.sv
module Stage3(clk, reset, branch_inst, reg_reg_inst, id_ex_a, id_ex_b, id_ex_npc, id_ex_ir, id_ex_imm, alu_op, ex_mem);
   input logic clk;
   input logic reset;
   input logic branch_inst;
   input logic reg_reg_inst;
   input logic [31:0] id_ex_a;
   input logic [31:0] id_ex_b;
   input logic [31:0] id_ex_npc;
   input logic [31:0] id_ex_ir;
   input logic [31:0] id_ex_imm;
   input logic [3:0]   alu_op;
   output logic [31:0] ex_mem [3:0];
   logic [31:0]        alu_a;
   logic [31:0]        alu_b;
   logic [31:0]        alu_out;
   
   

   always_comb begin
      if(reg_reg_inst) begin
         alu_b = id_ex_b;
      end
      else begin
         alu_b = id_ex_imm;
      end
   end
   ALU alu(id_ex_a, alu_b, alu_op, alu_out);
   
   always @(posedge clk) begin
      if(reset) begin
         ex_mem[0] <= 0;
         ex_mem[1] <= 0;
         ex_mem[2] <= 0;
      end
      else begin
         ex_mem[0] <= id_ex_ir; //IR
         ex_mem[1] <= 0; //COND
         ex_mem[2] <= alu_out; //ALU Output
         ex_mem[3] <= id_ex_b; // Register B
      end
      
      
   end
   
   
endmodule; // Stage3

src/Stage2.sv
module Stage2 (clk, reset, if_id_ir, if_id_npc, id_ex);
   input logic clk;
   input logic reset;

   input logic [31:0] if_id_ir;
   input logic [31:0] if_id_npc;
   

   
   
   output logic [31:0] id_ex [4:0];
   
   always @(posedge clk) begin
      if(reset) begin
         id_ex[0] <= 0;
         id_ex[1] <= 0;
         id_ex[2] <= 0;
         id_ex[3] <= 0;
         id_ex[4] <= 0;
      end
      else begin
         
         id_ex[2] <= if_id_npc;
         id_ex[3] <= if_id_ir;
         id_ex[4] <= $signed(if_id_ir[31:20]);
      end
      
      

   end
   
endmodule; // Stage2

src/IMem.sv
// Temporary Instruction Memory RAM, will eventually build ICache


module IMem (address, read_out);
   input logic [31:0] address;
   output logic [31:0] read_out;

   // 128 instruction maximum
   logic [31:0]        imem [2047:0];

   //NOT SYNTHESIZEABLE

   initial begin
      $readmemh("../software/main.hex", imem);
   end
   assign read_out = imem[address-1];

   
   
endmodule // IMem

src/Stage1.sv
// branch_cond corresponds to EX/MEM.cond
// pc_offfset_branch corresponds to EX/MEM.ALUOutput
module Stage1 (clk, reset, branch_cond, pc_offset_branch, if_id);
   input logic clk;
   input logic reset;
   
   input logic [31:0] pc_offset_branch;
   input logic        branch_cond;
   logic [31:0] pc;
   logic [31:0] npc;
   logic [31:0] ir;
   output logic [31:0] if_id [1:0];

   IMem mem(pc, ir);
   always @(posedge clk) begin
      if (reset) begin
         pc <= 0;
         npc <= 0;
         if_id[0] <= 0;
         if_id[1] <= 0;
      end
      else begin
         if(branch_cond) begin
            npc <= pc_offset_branch;
            pc <= pc_offset_branch;
         end
         else begin
            npc <= npc + 1;
            pc <= pc + 1;
         end
      end
   end
   assign if_id[0] = ir;
   assign if_id[1] = npc;
endmodule;

src/Datapath.sv
/*
 Controller controls:
 1. two muxes in execute stage
 2. write-back mux
 3. destination mux
 
 we need to figure out if the instruction is a:
  - branch (control top mux of exec)
  - reg_reg (control bottom mux of exec)
  - load_inst (control first wb mux)
  - mux to choose which part of IR is the correct reg_dest (control second wb mux) (reg_reg ALU vs ALU immediate/Load)
 
 */
module Datapath (clk, reset,/* id_ex, */current_opcode, current_func, branch_inst, reg_reg_inst, load_inst, reg_dest, alu_op, reg_array);
   input logic clk;
   input logic reset;
   input logic branch_inst;
   input logic reg_reg_inst;
   input logic load_inst;
   input logic reg_dest;
   input logic [3:0] alu_op;
   output logic [6:0] current_opcode;
   output logic [3:0] current_func;
   output logic [31:0] reg_array [31:0];
   
   
   
   // These two come from EX/MEM
   logic branch_taken;
   logic [31:0] pc_offset_branch;
   
   // IR, NPC 
   logic [31:0] if_id [1:0];
   assign current_opcode = id_ex[3][6:0];
   assign current_func = {id_ex[3][30], id_ex[3][14:12]};
   //a, b, npc, ir, imm
   logic [31:0] id_ex [4:0];
   //ir, cond, alu_output, b-register
   logic [31:0] ex_mem[3:0]; 

   // ir, alu_output, lmd, load_inst (for wb)
   logic [31:0] mem_wb [3:0];
   

   

   
   
   // Regfile has two read output ports, one for rs1, and one for rs2
   // wa is the write input
   

   logic [4:0] reg_wa;
   logic [31:0] wa_data;
   logic       reg_r_w;
   
   Stage1 s1 (clk, reset, ex_mem[1], ex_mem[2], if_id);
   Stage2 s2 (clk, reset, if_id[0], if_id[1], id_ex);
   Stage3 s3 (clk, reset, branch_inst, reg_reg_inst, id_ex[0], id_ex[1], id_ex[2], id_ex[3], id_ex[4], alu_op, ex_mem);
   Stage4 s4 (clk, reset, load_inst, ex_mem[0], ex_mem[2], ex_mem[3], mem_wb);
   
   
   
   Regfile regs(clk, reset, if_id[0][19:15], id_ex[0], if_id[0][24:20], id_ex[1], mem_wb[0][11:7], (mem_wb[3] == 0) ? mem_wb[1] : mem_wb[2], reg_r_w, reg_array);
   
   
   

endmodule; // Datapath

src/Core.sv
module Core (clk, reset, reg_array);
   input logic clk;
   input logic reset;
   // Has to implement Datapath and ControlUnit
   logic [6:0] current_opcode;
   logic [3:0] current_func;
   logic       branch_inst;
   logic       reg_reg_inst;
   logic       load_inst;
   logic       reg_dest;
   logic [3:0] alu_op;
   output logic [31:0] reg_array [31:0];
   
   Datapath dp(clk, reset, current_opcode, current_func, branch_inst, reg_reg_inst, load_inst, reg_dest, alu_op, reg_array);
   ControlUnit cu(clk, reset, current_opcode, current_func, branch_inst, reg_reg_inst, load_inst, reg_dest, alu_op);
//   always @(posedge clk) begin
//      $display("current_op: %b current_func: %b branch: %b reg: %b load: %b dest: alu_op: %b", current_opcode, current_func, branch_inst, reg_reg_inst, load_inst, reg_dest, alu_op);
//      
//   end
   
 

endmodule; // Core

tests/waveform.vcd
$version Generated by VerilatedVcd $end
$timescale 1ps $end

 $scope module TOP $end
  $var wire  1 M clk $end
  $var wire 32 O reg_array[0] [31:0] $end
  $var wire 32 Y reg_array[10] [31:0] $end
  $var wire 32 Z reg_array[11] [31:0] $end
  $var wire 32 [ reg_array[12] [31:0] $end
  $var wire 32 \ reg_array[13] [31:0] $end
  $var wire 32 ] reg_array[14] [31:0] $end
  $var wire 32 ^ reg_array[15] [31:0] $end
  $var wire 32 _ reg_array[16] [31:0] $end
  $var wire 32 ` reg_array[17] [31:0] $end
  $var wire 32 a reg_array[18] [31:0] $end
  $var wire 32 b reg_array[19] [31:0] $end
  $var wire 32 P reg_array[1] [31:0] $end
  $var wire 32 c reg_array[20] [31:0] $end
  $var wire 32 d reg_array[21] [31:0] $end
  $var wire 32 e reg_array[22] [31:0] $end
  $var wire 32 f reg_array[23] [31:0] $end
  $var wire 32 g reg_array[24] [31:0] $end
  $var wire 32 h reg_array[25] [31:0] $end
  $var wire 32 i reg_array[26] [31:0] $end
  $var wire 32 j reg_array[27] [31:0] $end
  $var wire 32 k reg_array[28] [31:0] $end
  $var wire 32 l reg_array[29] [31:0] $end
  $var wire 32 Q reg_array[2] [31:0] $end
  $var wire 32 m reg_array[30] [31:0] $end
  $var wire 32 n reg_array[31] [31:0] $end
  $var wire 32 R reg_array[3] [31:0] $end
  $var wire 32 S reg_array[4] [31:0] $end
  $var wire 32 T reg_array[5] [31:0] $end
  $var wire 32 U reg_array[6] [31:0] $end
  $var wire 32 V reg_array[7] [31:0] $end
  $var wire 32 W reg_array[8] [31:0] $end
  $var wire 32 X reg_array[9] [31:0] $end
  $var wire  1 N reset $end
  $scope module Core $end
   $var wire  4 ) alu_op [3:0] $end
   $var wire  1 % branch_inst $end
   $var wire  1 M clk $end
   $var wire  4 $ current_func [3:0] $end
   $var wire  7 # current_opcode [6:0] $end
   $var wire  1 ' load_inst $end
   $var wire 32 O reg_array[0] [31:0] $end
   $var wire 32 Y reg_array[10] [31:0] $end
   $var wire 32 Z reg_array[11] [31:0] $end
   $var wire 32 [ reg_array[12] [31:0] $end
   $var wire 32 \ reg_array[13] [31:0] $end
   $var wire 32 ] reg_array[14] [31:0] $end
   $var wire 32 ^ reg_array[15] [31:0] $end
   $var wire 32 _ reg_array[16] [31:0] $end
   $var wire 32 ` reg_array[17] [31:0] $end
   $var wire 32 a reg_array[18] [31:0] $end
   $var wire 32 b reg_array[19] [31:0] $end
   $var wire 32 P reg_array[1] [31:0] $end
   $var wire 32 c reg_array[20] [31:0] $end
   $var wire 32 d reg_array[21] [31:0] $end
   $var wire 32 e reg_array[22] [31:0] $end
   $var wire 32 f reg_array[23] [31:0] $end
   $var wire 32 g reg_array[24] [31:0] $end
   $var wire 32 h reg_array[25] [31:0] $end
   $var wire 32 i reg_array[26] [31:0] $end
   $var wire 32 j reg_array[27] [31:0] $end
   $var wire 32 k reg_array[28] [31:0] $end
   $var wire 32 l reg_array[29] [31:0] $end
   $var wire 32 Q reg_array[2] [31:0] $end
   $var wire 32 m reg_array[30] [31:0] $end
   $var wire 32 n reg_array[31] [31:0] $end
   $var wire 32 R reg_array[3] [31:0] $end
   $var wire 32 S reg_array[4] [31:0] $end
   $var wire 32 T reg_array[5] [31:0] $end
   $var wire 32 U reg_array[6] [31:0] $end
   $var wire 32 V reg_array[7] [31:0] $end
   $var wire 32 W reg_array[8] [31:0] $end
   $var wire 32 X reg_array[9] [31:0] $end
   $var wire  1 ( reg_dest $end
   $var wire  1 & reg_reg_inst $end
   $var wire  1 N reset $end
   $scope module cu $end
    $var wire  4 ) alu_op [3:0] $end
    $var wire  1 % branch_inst $end
    $var wire  1 M clk $end
    $var wire  4 $ current_func [3:0] $end
    $var wire  7 # current_opcode [6:0] $end
    $var wire  1 * delayed_load_inst $end
    $var wire  1 ' load_inst $end
    $var wire  1 ( reg_dest $end
    $var wire  1 & reg_reg_inst $end
    $var wire  1 N reset $end
   $upscope $end
   $scope module dp $end
    $var wire  4 ) alu_op [3:0] $end
    $var wire  1 % branch_inst $end
    $var wire  1 o branch_taken $end
    $var wire  1 M clk $end
    $var wire  4 $ current_func [3:0] $end
    $var wire  7 # current_opcode [6:0] $end
    $var wire 32 2 ex_mem[0] [31:0] $end
    $var wire 32 3 ex_mem[1] [31:0] $end
    $var wire 32 4 ex_mem[2] [31:0] $end
    $var wire 32 5 ex_mem[3] [31:0] $end
    $var wire 32 - id_ex[0] [31:0] $end
    $var wire 32 . id_ex[1] [31:0] $end
    $var wire 32 / id_ex[2] [31:0] $end
    $var wire 32 0 id_ex[3] [31:0] $end
    $var wire 32 1 id_ex[4] [31:0] $end
    $var wire 32 + if_id[0] [31:0] $end
    $var wire 32 , if_id[1] [31:0] $end
    $var wire  1 ' load_inst $end
    $var wire 32 6 mem_wb[0] [31:0] $end
    $var wire 32 7 mem_wb[1] [31:0] $end
    $var wire 32 8 mem_wb[2] [31:0] $end
    $var wire 32 9 mem_wb[3] [31:0] $end
    $var wire 32 p pc_offset_branch [31:0] $end
    $var wire 32 O reg_array[0] [31:0] $end
    $var wire 32 Y reg_array[10] [31:0] $end
    $var wire 32 Z reg_array[11] [31:0] $end
    $var wire 32 [ reg_array[12] [31:0] $end
    $var wire 32 \ reg_array[13] [31:0] $end
    $var wire 32 ] reg_array[14] [31:0] $end
    $var wire 32 ^ reg_array[15] [31:0] $end
    $var wire 32 _ reg_array[16] [31:0] $end
    $var wire 32 ` reg_array[17] [31:0] $end
    $var wire 32 a reg_array[18] [31:0] $end
    $var wire 32 b reg_array[19] [31:0] $end
    $var wire 32 P reg_array[1] [31:0] $end
    $var wire 32 c reg_array[20] [31:0] $end
    $var wire 32 d reg_array[21] [31:0] $end
    $var wire 32 e reg_array[22] [31:0] $end
    $var wire 32 f reg_array[23] [31:0] $end
    $var wire 32 g reg_array[24] [31:0] $end
    $var wire 32 h reg_array[25] [31:0] $end
    $var wire 32 i reg_array[26] [31:0] $end
    $var wire 32 j reg_array[27] [31:0] $end
    $var wire 32 k reg_array[28] [31:0] $end
    $var wire 32 l reg_array[29] [31:0] $end
    $var wire 32 Q reg_array[2] [31:0] $end
    $var wire 32 m reg_array[30] [31:0] $end
    $var wire 32 n reg_array[31] [31:0] $end
    $var wire 32 R reg_array[3] [31:0] $end
    $var wire 32 S reg_array[4] [31:0] $end
    $var wire 32 T reg_array[5] [31:0] $end
    $var wire 32 U reg_array[6] [31:0] $end
    $var wire 32 V reg_array[7] [31:0] $end
    $var wire 32 W reg_array[8] [31:0] $end
    $var wire 32 X reg_array[9] [31:0] $end
    $var wire  1 ( reg_dest $end
    $var wire  1 s reg_r_w $end
    $var wire  1 & reg_reg_inst $end
    $var wire  5 q reg_wa [4:0] $end
    $var wire  1 N reset $end
    $var wire 32 r wa_data [31:0] $end
    $scope module regs $end
     $var wire  1 M clk $end
     $var wire 32 < ra_data [31:0] $end
     $var wire 32 = rb_data [31:0] $end
     $var wire  5 : reg_a [4:0] $end
     $var wire 32 O reg_array[0] [31:0] $end
     $var wire 32 Y reg_array[10] [31:0] $end
     $var wire 32 Z reg_array[11] [31:0] $end
     $var wire 32 [ reg_array[12] [31:0] $end
     $var wire 32 \ reg_array[13] [31:0] $end
     $var wire 32 ] reg_array[14] [31:0] $end
     $var wire 32 ^ reg_array[15] [31:0] $end
     $var wire 32 _ reg_array[16] [31:0] $end
     $var wire 32 ` reg_array[17] [31:0] $end
     $var wire 32 a reg_array[18] [31:0] $end
     $var wire 32 b reg_array[19] [31:0] $end
     $var wire 32 P reg_array[1] [31:0] $end
     $var wire 32 c reg_array[20] [31:0] $end
     $var wire 32 d reg_array[21] [31:0] $end
     $var wire 32 e reg_array[22] [31:0] $end
     $var wire 32 f reg_array[23] [31:0] $end
     $var wire 32 g reg_array[24] [31:0] $end
     $var wire 32 h reg_array[25] [31:0] $end
     $var wire 32 i reg_array[26] [31:0] $end
     $var wire 32 j reg_array[27] [31:0] $end
     $var wire 32 k reg_array[28] [31:0] $end
     $var wire 32 l reg_array[29] [31:0] $end
     $var wire 32 Q reg_array[2] [31:0] $end
     $var wire 32 m reg_array[30] [31:0] $end
     $var wire 32 n reg_array[31] [31:0] $end
     $var wire 32 R reg_array[3] [31:0] $end
     $var wire 32 S reg_array[4] [31:0] $end
     $var wire 32 T reg_array[5] [31:0] $end
     $var wire 32 U reg_array[6] [31:0] $end
     $var wire 32 V reg_array[7] [31:0] $end
     $var wire 32 W reg_array[8] [31:0] $end
     $var wire 32 X reg_array[9] [31:0] $end
     $var wire  5 ; reg_b [4:0] $end
     $var wire  1 s reg_r_w $end
     $var wire  5 > reg_wa [4:0] $end
     $var wire  1 N reset $end
     $var wire 32 ? wa_data [31:0] $end
    $upscope $end
    $scope module s1 $end
     $var wire  1 A branch_cond $end
     $var wire  1 M clk $end
     $var wire 32 + if_id[0] [31:0] $end
     $var wire 32 , if_id[1] [31:0] $end
     $var wire 32 D ir [31:0] $end
     $var wire 32 C npc [31:0] $end
     $var wire 32 B pc [31:0] $end
     $var wire 32 @ pc_offset_branch [31:0] $end
     $var wire  1 N reset $end
     $scope module mem $end
      $var wire 32 B address [31:0] $end
      $var wire 32 D read_out [31:0] $end
     $upscope $end
    $upscope $end
    $scope module s2 $end
     $var wire  1 M clk $end
     $var wire 32 - id_ex[0] [31:0] $end
     $var wire 32 . id_ex[1] [31:0] $end
     $var wire 32 / id_ex[2] [31:0] $end
     $var wire 32 0 id_ex[3] [31:0] $end
     $var wire 32 1 id_ex[4] [31:0] $end
     $var wire 32 D if_id_ir [31:0] $end
     $var wire 32 C if_id_npc [31:0] $end
     $var wire  1 N reset $end
    $upscope $end
    $scope module s3 $end
     $var wire 32 t alu_a [31:0] $end
     $var wire 32 H alu_b [31:0] $end
     $var wire  4 ) alu_op [3:0] $end
     $var wire 32 I alu_out [31:0] $end
     $var wire  1 % branch_inst $end
     $var wire  1 M clk $end
     $var wire 32 2 ex_mem[0] [31:0] $end
     $var wire 32 3 ex_mem[1] [31:0] $end
     $var wire 32 4 ex_mem[2] [31:0] $end
     $var wire 32 5 ex_mem[3] [31:0] $end
     $var wire 32 < id_ex_a [31:0] $end
     $var wire 32 = id_ex_b [31:0] $end
     $var wire 32 G id_ex_imm [31:0] $end
     $var wire 32 F id_ex_ir [31:0] $end
     $var wire 32 E id_ex_npc [31:0] $end
     $var wire  1 & reg_reg_inst $end
     $var wire  1 N reset $end
     $scope module alu $end
      $var wire 32 < alu_a [31:0] $end
      $var wire 32 H alu_b [31:0] $end
      $var wire  4 ) alu_op [3:0] $end
      $var wire 32 I alu_out [31:0] $end
     $upscope $end
    $upscope $end
    $scope module s4 $end
     $var wire  1 M clk $end
     $var wire 32 @ ex_mem_alu_output [31:0] $end
     $var wire 32 K ex_mem_b [31:0] $end
     $var wire 32 J ex_mem_ir [31:0] $end
     $var wire  1 ' load_inst $end
     $var wire 32 u mem_out [31:0] $end
     $var wire 32 6 mem_wb[0] [31:0] $end
     $var wire 32 7 mem_wb[1] [31:0] $end
     $var wire 32 8 mem_wb[2] [31:0] $end
     $var wire 32 9 mem_wb[3] [31:0] $end
     $var wire  1 v r_w $end
     $var wire  1 N reset $end
     $scope module dm $end
      $var wire 32 @ address [31:0] $end
      $var wire  1 M clk $end
      $var wire  1 ' en $end
      $var wire 32 K in [31:0] $end
      $var wire 32 L out [31:0] $end
      $var wire  1 v r_w $end
     $upscope $end
    $upscope $end
   $upscope $end
  $upscope $end
 $upscope $end
$enddefinitions $end


#8
b0000000 #
b0000 $
0%
0&
0'
0(
b0000 )
0*
b00000000000000000000000000000000 +
b00000000000000000000000000000000 ,
b00000000000000000000000000000000 -
b00000000000000000000000000000000 .
b00000000000000000000000000000000 /
b00000000000000000000000000000000 0
b00000000000000000000000000000000 1
b00000000000000000000000000000000 2
b00000000000000000000000000000000 3
b00000000000000000000000000000000 4
b00000000000000000000000000000000 5
b00000000000000000000000000000000 6
b00000000000000000000000000000000 7
b00000000000000000000000000000000 8
b00000000000000000000000000000000 9
b00000 :
b00000 ;
b00000000000000000000000000000000 <
b00000000000000000000000000000000 =
b00000 >
b00000000000000000000000000000000 ?
b00000000000000000000000000000000 @
0A
b00000000000000000000000000000000 B
b00000000000000000000000000000000 C
b00000000000000000000000000000000 D
b00000000000000000000000000000000 E
b00000000000000000000000000000000 F
b00000000000000000000000000000000 G
b00000000000000000000000000000000 H
b00000000000000000000000000000000 I
b00000000000000000000000000000000 J
b00000000000000000000000000000000 K
b00000000000000000000000000000000 L
0M
0N
b00000000000000000000000000000000 O
b00000000000000000000000000000000 P
b00000000000000000000000000000000 Q
b00000000000000000000000000000000 R
b00000000000000000000000000000000 S
b00000000000000000000000000000000 T
b00000000000000000000000000000000 U
b00000000000000000000000000000000 V
b00000000000000000000000000000000 W
b00000000000000000000000000000000 X
b00000000000000000000000000000000 Y
b00000000000000000000000000000000 Z
b00000000000000000000000000000000 [
b00000000000000000000000000000000 \
b00000000000000000000000000000000 ]
b00000000000000000000000000000000 ^
b00000000000000000000000000000000 _
b00000000000000000000000000000000 `
b00000000000000000000000000000000 a
b00000000000000000000000000000000 b
b00000000000000000000000000000000 c
b00000000000000000000000000000000 d
b00000000000000000000000000000000 e
b00000000000000000000000000000000 f
b00000000000000000000000000000000 g
b00000000000000000000000000000000 h
b00000000000000000000000000000000 i
b00000000000000000000000000000000 j
b00000000000000000000000000000000 k
b00000000000000000000000000000000 l
b00000000000000000000000000000000 m
b00000000000000000000000000000000 n
0o
b00000000000000000000000000000000 p
b00000 q
b00000000000000000000000000000000 r
0s
b00000000000000000000000000000000 t
b00000000000000000000000000000000 u
0v
#10
b00000000011000000000001100010011 +
b00000000000000000000000000000001 ,
b00110 ;
b00000000000000000000000000000001 B
b00000000000000000000000000000001 C
b00000000011000000000001100010011 D
1M
#15
0M
#18
#20
b0010011 #
b0001 )
b00000000011100000000001110010011 +
b00000000000000000000000000000010 ,
b00000000000000000000000000000001 /
b00000000011000000000001100010011 0
b00000000000000000000000000000110 1
b00111 ;
b00000000000000000000000000000010 B
b00000000000000000000000000000010 C
b00000000011100000000001110010011 D
b00000000000000000000000000000001 E
b00000000011000000000001100010011 F
b00000000000000000000000000000110 G
b00000000000000000000000000000110 H
b00000000000000000000000000000110 I
1M
#25
0M
#28
#30
b11000001100000000000000010010011 +
b00000000000000000000000000000011 ,
b00000000000000000000000000000010 /
b00000000011100000000001110010011 0
b00000000000000000000000000000111 1
b00000000011000000000001100010011 2
b00000000000000000000000000000110 4
b11000 ;
b00000000000000000000000000000110 @
b00000000000000000000000000000011 B
b00000000000000000000000000000011 C
b11000001100000000000000010010011 D
b00000000000000000000000000000010 E
b00000000011100000000001110010011 F
b00000000000000000000000000000111 G
b00000000000000000000000000000111 H
b00000000000000000000000000000111 I
b00000000011000000000001100010011 J
1M
#35
0M
#38
#40
b1000 $
b00000000000000000000000000010011 +
b00000000000000000000000000000100 ,
b00000000000000000000000000000011 /
b11000001100000000000000010010011 0
b11111111111111111111110000011000 1
b00000000011100000000001110010011 2
b00000000000000000000000000000111 4
b00000000011000000000001100010011 6
b00000000000000000000000000000110 7
b00000 ;
b00110 >
b00000000000000000000000000000110 ?
b00000000000000000000000000000111 @
b00000000000000000000000000000100 B
b00000000000000000000000000000100 C
b00000000000000000000000000010011 D
b00000000000000000000000000000011 E
b11000001100000000000000010010011 F
b11111111111111111111110000011000 G
b11111111111111111111110000011000 H
b11111111111111111111110000011000 I
b00000000011100000000001110010011 J
1M
#45
0M
#48
#50
b0000 $
b00000000000000000000000000000101 ,
b00000000000000000000000000000100 /
b00000000000000000000000000010011 0
b00000000000000000000000000000000 1
b11000001100000000000000010010011 2
b11111111111111111111110000011000 4
b00000000011100000000001110010011 6
b00000000000000000000000000000111 7
b00111 >
b00000000000000000000000000000111 ?
b11111111111111111111110000011000 @
b00000000000000000000000000000101 B
b00000000000000000000000000000101 C
b00000000000000000000000000000100 E
b00000000000000000000000000010011 F
b00000000000000000000000000000000 G
b00000000000000000000000000000000 H
b00000000000000000000000000000000 I
b11000001100000000000000010010011 J
1M
b00000000000000000000000000000110 U
#55
0M
#58
#60
b00000000000000000000000000000110 ,
b00000000000000000000000000000101 /
b00000000000000000000000000010011 2
b00000000000000000000000000000000 4
b11000001100000000000000010010011 6
b11111111111111111111110000011000 7
b00001 >
b11111111111111111111110000011000 ?
b00000000000000000000000000000000 @
b00000000000000000000000000000110 B
b00000000000000000000000000000110 C
b00000000000000000000000000000101 E
b00000000000000000000000000010011 J
1M
b00000000000000000000000000000111 V
#65
0M
#68
#70
b00000000000000000000000000000111 ,
b00000000000000000000000000000110 /
b00000000000000000000000000010011 6
b00000000000000000000000000000000 7
b00000 >
b00000000000000000000000000000000 ?
b00000000000000000000000000000111 B
b00000000000000000000000000000111 C
b00000000000000000000000000000110 E
1M
b11111111111111111111110000011000 P
#75
0M
#78
#80
b00000000011100110000001010110011 +
b00000000000000000000000000001000 ,
b00000000000000000000000000000111 /
b00110 :
b00111 ;
b00000000000000000000000000001000 B
b00000000000000000000000000001000 C
b00000000011100110000001010110011 D
b00000000000000000000000000000111 E
1M
#85
0M
#88
#90
b0110011 #
1&
b01000000011100110000010000110011 +
b00000000000000000000000000001001 ,
b00000000000000000000000000000110 -
b00000000000000000000000000000111 .
b00000000000000000000000000001000 /
b00000000011100110000001010110011 0
b00000000000000000000000000000111 1
b00000000000000000000000000000110 <
b00000000000000000000000000000111 =
b00000000000000000000000000001001 B
b00000000000000000000000000001001 C
b01000000011100110000010000110011 D
b00000000000000000000000000001000 E
b00000000011100110000001010110011 F
b00000000000000000000000000000111 G
b00000000000000000000000000000111 H
b00000000000000000000000000001101 I
1M
#95
0M
#98
